github_api_sdk/__init__.py
github_api_sdk/_base_client.py
github_api_sdk/_client.py
github_api_sdk/_compat.py
github_api_sdk/_constants.py
github_api_sdk/_exceptions.py
github_api_sdk/_files.py
github_api_sdk/_models.py
github_api_sdk/_qs.py
github_api_sdk/_resource.py
github_api_sdk/_response.py
github_api_sdk/_streaming.py
github_api_sdk/_types.py
github_api_sdk/_version.py
github_api_sdk/py.typed
github_api_sdk/_utils/__init__.py
github_api_sdk/_utils/_logs.py
github_api_sdk/_utils/_proxy.py
github_api_sdk/_utils/_reflection.py
github_api_sdk/_utils/_streams.py
github_api_sdk/_utils/_sync.py
github_api_sdk/_utils/_transform.py
github_api_sdk/_utils/_typing.py
github_api_sdk/_utils/_utils.py
github_api_sdk/resources/__init__.py
github_api_sdk/resources/advisories.py
github_api_sdk/resources/app_manifests.py
github_api_sdk/resources/assignments.py
github_api_sdk/resources/classrooms.py
github_api_sdk/resources/codes_of_conduct.py
github_api_sdk/resources/emojis.py
github_api_sdk/resources/events.py
github_api_sdk/resources/feeds.py
github_api_sdk/resources/installation.py
github_api_sdk/resources/issues.py
github_api_sdk/resources/licenses.py
github_api_sdk/resources/markdown.py
github_api_sdk/resources/meta.py
github_api_sdk/resources/networks.py
github_api_sdk/resources/octocat.py
github_api_sdk/resources/rate_limit.py
github_api_sdk/resources/repositories.py
github_api_sdk/resources/zen.py
github_api_sdk/resources/applications/__init__.py
github_api_sdk/resources/applications/applications.py
github_api_sdk/resources/applications/hook/__init__.py
github_api_sdk/resources/applications/hook/config.py
github_api_sdk/resources/applications/hook/deliveries.py
github_api_sdk/resources/applications/hook/hook.py
github_api_sdk/resources/applications/installations/__init__.py
github_api_sdk/resources/applications/installations/installations.py
github_api_sdk/resources/applications/installations/suspended.py
github_api_sdk/resources/enterprises/__init__.py
github_api_sdk-0.0.2.dist-info/METADATA
github_api_sdk-0.0.2.dist-info/WHEEL
github_api_sdk-0.0.2.dist-info/top_level.txt
github_api_sdk-0.0.2.dist-info/RECORD
